[
  {
    "id": 1764964604658,
    "slug": "teste-2",
    "title": "Teste 2",
    "excerpt": "Todo o conteúdo por aqui...",
    "content": "<p>Todo o conteúdo por aqui</p>",
    "date": "05/12/2025",
    "author": "Admin",
    "category": "Geral",
    "imageUrl": ""
  },
  {
    "id": 1764111304506,
    "slug": "teste-1-teste-de-verdade",
    "title": "Teste 1 TESTE DE VERDADE",
    "excerpt": "Teste 1\r\n...",
    "content": "Teste 1\r\n",
    "date": "25/11/2025",
    "author": "Admin",
    "category": "Geral",
    "imageUrl": "/uploads/1764964574862-IMG_4932.JPG"
  },
  {
    "id": 1,
    "slug": "post-de-exemplo",
    "title": "Post de Exemplo",
    "excerpt": "Conteúdo de teste persistente....",
    "content": "Conteúdo de teste persistente.",
    "date": "25/11/2025",
    "author": "Admin",
    "category": "Geral",
    "imageUrl": ""
  }
]